odoo/addons/ssi_task_timebox/README.rst
odoo/addons/ssi_task_timebox/__init__.py
odoo/addons/ssi_task_timebox/__manifest__.py
odoo/addons/ssi_task_timebox/data/base_automation_data.xml
odoo/addons/ssi_task_timebox/data/ir_actions_server_data.xml
odoo/addons/ssi_task_timebox/i18n/ssi_task_timebox.pot
odoo/addons/ssi_task_timebox/models/__init__.py
odoo/addons/ssi_task_timebox/models/project_project.py
odoo/addons/ssi_task_timebox/models/project_task.py
odoo/addons/ssi_task_timebox/models/task_dependency.py
odoo/addons/ssi_task_timebox/models/task_timebox.py
odoo/addons/ssi_task_timebox/security/ir.model.access.csv
odoo/addons/ssi_task_timebox/security/res_group_data.xml
odoo/addons/ssi_task_timebox/static/description/icon.png
odoo/addons/ssi_task_timebox/views/project_project_views.xml
odoo/addons/ssi_task_timebox/views/project_task_views.xml
odoo/addons/ssi_task_timebox/views/task_timebox_views.xml
odoo/addons/ssi_task_timebox/wizards/__init__.py
odoo/addons/ssi_task_timebox/wizards/create_sucessor_task.py
odoo/addons/ssi_task_timebox/wizards/create_sucessor_task.xml
odoo14_addon_ssi_task_timebox-14.0.4.1.0.dist-info/METADATA
odoo14_addon_ssi_task_timebox-14.0.4.1.0.dist-info/WHEEL
odoo14_addon_ssi_task_timebox-14.0.4.1.0.dist-info/top_level.txt
odoo14_addon_ssi_task_timebox-14.0.4.1.0.dist-info/RECORD
